{
  "_metadata": {
    "source": "https://simbli.eboardsolutions.com/Policy/ViewPolicy.aspx?S=36030397&revid=Cs6plus57jcw0UyqRJedy3eVQ==",
    "scrapedAt": "2026-05-24T20:11:49.868Z",
    "method": "Playwright + Simbli ViewPolicy API scraper"
  },
  "code": "3555-E PDF(1)",
  "title": "Nutrition Program Compliance",
  "type": "AR",
  "section": "3000",
  "lastRevised": "02/09/2022",
  "lastReviewed": "02/09/2022",
  "hasAttachment": false,
  "revid": "Cs6plus57jcw0UyqRJedy3eVQ==",
  "contentHtml": "",
  "contentText": "",
  "footnotes": [
    {
      "type": "State",
      "references": [
        {
          "code": "5 CCR 15580-15584",
          "description": "Child nutrition programs complaint procedures",
          "url": "https://govt.westlaw.com/calregs/Browse/Home/California/CaliforniaCodeofRegulations?guid=I4431E3804C6911EC93A8000D3A7C4BC3&transitionType=Default&contextData=%28sc.Default%29#I4433B8444C6911EC93A8000D3A7C4BC3"
        },
        {
          "code": "5 CCR 3080",
          "description": "Applicability of uniform complaint procedures to complaints regarding students with disabilities",
          "url": "https://govt.westlaw.com/calregs/Document/I31E45F534C6911EC93A8000D3A7C4BC3?viewType=FullText&originationContext=documenttoc&transitionType=CategoryPageItem&contextData=(sc.Default)"
        },
        {
          "code": "5 CCR 4600-4670",
          "description": "Uniform complaint procedures",
          "url": "https://govt.westlaw.com/calregs/Browse/Home/California/CaliforniaCodeofRegulations?guid=I344559C04C6911EC93A8000D3A7C4BC3&originationContext=documenttoc&transitionType=Default&contextData=(sc.Default)"
        },
        {
          "code": "5 CCR 4900-4965",
          "description": "Nondiscrimination in elementary and secondary educational programs receiving state or federal financial assistance",
          "url": ""
        },
        {
          "code": "Ed. Code 200-262.4",
          "description": "Prohibition of discrimination",
          "url": "http://leginfo.legislature.ca.gov/faces/codes_displayText.xhtml?division=1.&chapter=2.&part=1.&lawCode=EDC&title=1.&article=1."
        },
        {
          "code": "Ed. Code 42238.01 ",
          "description": "Definitions for purposes of funding",
          "url": "https://leginfo.legislature.ca.gov/faces/codes_displaySection.xhtml?lawCode=EDC&sectionNum=42238.01."
        },
        {
          "code": "Ed. Code 48985",
          "description": "Notices to parents/guardians in language other than English",
          "url": "https://leginfo.legislature.ca.gov/faces/codes_displaySection.xhtml?lawCode=EDC&sectionNum=48985."
        },
        {
          "code": "Ed. Code 49060-49079",
          "description": "Student records",
          "url": "https://leginfo.legislature.ca.gov/faces/codes_displayexpandedbranch.xhtml?tocCode=EDC&division=4.&title=2.&part=27.&chapter=6.5.&article="
        },
        {
          "code": "Ed. Code 49490-49590",
          "description": "Child nutrition programs",
          "url": "https://leginfo.legislature.ca.gov/faces/codes_displayexpandedbranch.xhtml?tocCode=EDC&division=&title=2.&part=&chapter=&article=&nodetreepath=2"
        },
        {
          "code": "Pen. Code 422.6",
          "description": "Crimes; harassment",
          "url": "https://leginfo.legislature.ca.gov/faces/codes_displaySection.xhtml?lawCode=PEN&sectionNum=422.6."
        }
      ]
    },
    {
      "type": "Federal",
      "references": [
        {
          "code": "20 USC 1400-1482",
          "description": "Individuals with Disabilities Education Act",
          "url": "https://uscode.house.gov/view.xhtml?path=/prelim@title20/chapter33&edition=prelim"
        },
        {
          "code": "20 USC 1681-1688",
          "description": "Title IX of the Education Amendments of 1972; discrimination based on sex",
          "url": ""
        },
        {
          "code": "28 CFR 35.101-35.190",
          "description": "Americans with Disabilities Act",
          "url": ""
        },
        {
          "code": "28 CFR 36.303",
          "description": "Nondiscrimination on the basis of disability; public accommodations, auxiliary aids, and services",
          "url": "https://www.ecfr.gov/current/title-28/chapter-I/part-36/subpart-C/section-36.303"
        },
        {
          "code": "29 USC 794",
          "description": "Rehabilitation Act of 1973; Section 504",
          "url": "https://uscode.house.gov/view.xhtml?req=(title:29%20section:794%20edition:prelim)%20OR%20(granuleid:USC-prelim-title29-section794)&f=treesort&edition=prelim&num=0&jumpTo=true"
        },
        {
          "code": "34 CFR 100.1-100.13",
          "description": "Nondiscrimination in federal programs; effectuating Title VI",
          "url": "https://www.ecfr.gov/current/title-34/subtitle-B/chapter-I/part-100"
        },
        {
          "code": "34 CFR 104.1-104.39",
          "description": "Section 504 of the Rehabilitation Act of 1973",
          "url": ""
        },
        {
          "code": "34 CFR 106.1-106.61",
          "description": "Discrimination on the basis of sex; effectuating Title IX",
          "url": ""
        },
        {
          "code": "34 CFR 106.9",
          "description": "Severability",
          "url": "https://www.ecfr.gov/current/title-34/subtitle-B/chapter-I/part-106/subpart-A/section-106.9"
        },
        {
          "code": "42 USC 12101-12213",
          "description": "Americans with Disabilities Act",
          "url": "https://uscode.house.gov/view.xhtml?path=/prelim@title42/chapter126&edition=prelim"
        },
        {
          "code": "42 USC 2000d-2000d-7",
          "description": "Title VI, Civil Rights Act of 1964",
          "url": ""
        },
        {
          "code": "42 USC 2000e-2000e-17",
          "description": "Title VII, Civil Rights Act of 1964, as amended",
          "url": ""
        },
        {
          "code": "7 CFR 210.19",
          "description": "National School Lunch Program; additional responsibilities",
          "url": "https://www.ecfr.gov/current/title-7/subtitle-B/chapter-II/subchapter-A/part-210/subpart-D/section-210.19"
        },
        {
          "code": "7 CFR 210.23",
          "description": "National School Lunch Program; district responsibilities",
          "url": "https://www.ecfr.gov/current/title-7/subtitle-B/chapter-II/subchapter-A/part-210/subpart-E/section-210.23"
        },
        {
          "code": "7 CFR 215.14",
          "description": "Special Milk Program; nondiscrimination",
          "url": "https://www.ecfr.gov/current/title-7/subtitle-B/chapter-II/subchapter-A/part-215/section-215.14"
        },
        {
          "code": "7 CFR 215.7",
          "description": "Special Milk Program; requirements for participation",
          "url": "https://www.ecfr.gov/current/title-7/subtitle-B/chapter-II/subchapter-A/part-215/section-215.7"
        },
        {
          "code": "7 CFR 220.13",
          "description": "School Breakfast Program; special responsibilities of state agencies",
          "url": "https://www.ecfr.gov/current/title-7/subtitle-B/chapter-II/subchapter-A/part-220/section-220.13"
        },
        {
          "code": "7 CFR 220.7",
          "description": "School Breakfast Program; requirements for participation",
          "url": "https://www.ecfr.gov/current/title-7/subtitle-B/chapter-II/subchapter-A/part-220/section-220.7"
        },
        {
          "code": "7 CFR 225.11",
          "description": "Summer Food Service Program; corrective action procedures",
          "url": "https://www.ecfr.gov/current/title-7/subtitle-B/chapter-II/subchapter-A/part-225/subpart-B/section-225.11"
        },
        {
          "code": "7 CFR 225.3",
          "description": "Summer Food Service Program; administration",
          "url": "https://www.ecfr.gov/current/title-7/subtitle-B/chapter-II/subchapter-A/part-225/subpart-A/section-225.3"
        },
        {
          "code": "7 CFR 225.7",
          "description": "Summer Food Service Program; program monitoring",
          "url": "https://www.ecfr.gov/current/title-7/subtitle-B/chapter-II/subchapter-A/part-225/subpart-B/section-225.7"
        },
        {
          "code": "7 CFR 226.6",
          "description": "Child and Adult Care Food Program; state agency administrative responsibilities",
          "url": "https://www.ecfr.gov/current/title-7/subtitle-B/chapter-II/subchapter-A/part-226/subpart-C/section-226.6"
        },
        {
          "code": "7 CFR 250.15",
          "description": "Out-of-condition donated foods, food recalls, and complaints",
          "url": "https://www.ecfr.gov/current/title-7/subtitle-B/chapter-II/subchapter-B/part-250/subpart-B/section-250.15"
        }
      ]
    },
    {
      "type": "Management Resources",
      "references": [
        {
          "code": "California Department of Education Publication",
          "description": "Civil Rights and Complaint Procedures, U.S. Department of Agriculture Child Nutrition Programs, June 2018",
          "url": "https://www.cde.ca.gov/"
        },
        {
          "code": "U. S. Department of Agriculture Publication",
          "description": "USDA Nondiscrimination Statement, December 2022",
          "url": "https://www.usda.gov/non-discrimination-statement"
        },
        {
          "code": "U.S. Department of Agriculture Publication",
          "description": "Application of Bostock v. Clayton County to Program Discrimination Complaint Processing – Policy Update, CRD 01-2022, May 2022",
          "url": "https://www.fns.usda.gov/cr/cr-02-2022"
        },
        {
          "code": "U.S. Department of Agriculture Publication",
          "description": "Civil Rights Compliance and Enforcement - Nutrition Programs and Activities, FNS Instruction 113-1, November 2005",
          "url": "https://www.fns.usda.gov/cr/fns-instruction-113-1"
        },
        {
          "code": "U.S. DOE Office for Civil Rights Publication",
          "description": "Notice of Non-Discrimination, August 2010",
          "url": "https://www.ed.gov/media/document/nondiscpdf-33795.pdf"
        },
        {
          "code": "Website",
          "description": "U. S. Department of Agriculture, And Justice for All Posters",
          "url": "https://ipa.osu.edu/about-us/usda-and-justice-all-poster"
        },
        {
          "code": "Website",
          "description": "CSBA District and County Office of Education Legal Services",
          "url": "https://legalservices.csba.org/"
        },
        {
          "code": "Website",
          "description": "U.S. Department of Agriculture, Office for Civil Rights",
          "url": "http://www.ascr.usda.gov"
        },
        {
          "code": "Website",
          "description": "U.S. Department of Agriculture, Food and Nutrition Service",
          "url": "http://www.fns.usda.gov"
        },
        {
          "code": "Website",
          "description": "California Department of Education, School Nutrition",
          "url": "https://www.cde.ca.gov/ls/nu/sn/"
        },
        {
          "code": "Website",
          "description": "U.S. Department of Education, Office for Civil Rights",
          "url": "http://www2.ed.gov/ocr"
        }
      ]
    }
  ],
  "crossRefs": [
    {
      "code": "0410",
      "title": "Nondiscrimination In District Programs And Activities",
      "type": "AR"
    },
    {
      "code": "1100",
      "title": "Communication With The Public",
      "type": "AR"
    },
    {
      "code": "1312.1",
      "title": "Complaints Concerning District Employees",
      "type": "AR"
    },
    {
      "code": "1312.1",
      "title": "Complaints Concerning District Employees",
      "type": "AR"
    },
    {
      "code": "1312.3",
      "title": "Uniform Complaint Procedures",
      "type": "AR"
    },
    {
      "code": "1312.3",
      "title": "Uniform Complaint Procedures",
      "type": "AR"
    },
    {
      "code": "1445",
      "title": "Response To Immigration Enforcement",
      "type": "AR"
    },
    {
      "code": "3312",
      "title": "Contracts",
      "type": "AR"
    },
    {
      "code": "3550",
      "title": "Food Service/Child Nutrition Program",
      "type": "AR"
    },
    {
      "code": "3550",
      "title": "Food Service/Child Nutrition Program",
      "type": "AR"
    },
    {
      "code": "3551",
      "title": "Food Service Operations/Cafeteria Fund",
      "type": "AR"
    },
    {
      "code": "3551",
      "title": "Food Service Operations/Cafeteria Fund",
      "type": "AR"
    },
    {
      "code": "3553",
      "title": "Free And Reduced Price Meals",
      "type": "AR"
    },
    {
      "code": "3553",
      "title": "Free And Reduced Price Meals",
      "type": "AR"
    },
    {
      "code": "4231",
      "title": "Staff Development",
      "type": "AR"
    },
    {
      "code": "5022",
      "title": "Student And Family Privacy Rights",
      "type": "AR"
    },
    {
      "code": "5022",
      "title": "Student And Family Privacy Rights",
      "type": "AR"
    },
    {
      "code": "5030",
      "title": "Student Wellness",
      "type": "AR"
    },
    {
      "code": "5125",
      "title": "Student Records",
      "type": "AR"
    },
    {
      "code": "5125",
      "title": "Student Records",
      "type": "AR"
    },
    {
      "code": "5141.27",
      "title": "Food Allergies/Special Dietary Needs",
      "type": "AR"
    },
    {
      "code": "5141.27",
      "title": "Food Allergies/Special Dietary Needs",
      "type": "AR"
    },
    {
      "code": "5145.6",
      "title": "Parent/Guardian Notifications",
      "type": "AR"
    },
    {
      "code": "5145.6-E PDF(1)",
      "title": "Parent/Guardian Notifications",
      "type": "AR"
    },
    {
      "code": "6159",
      "title": "Individualized Education Program",
      "type": "AR"
    },
    {
      "code": "6159",
      "title": "Individualized Education Program",
      "type": "AR"
    },
    {
      "code": "6164.6",
      "title": "Identification And Education Under Section 504",
      "type": "AR"
    },
    {
      "code": "6164.6",
      "title": "Identification And Education Under Section 504",
      "type": "AR"
    }
  ],
  "attachments": []
}
