{
  "code": "4140",
  "title": "Bargaining Units",
  "type": "BP",
  "section": "4000",
  "lastRevised": "11/04/2009",
  "lastReviewed": "11/04/2009",
  "hasAttachment": false,
  "revid": "Tkuslsh6ya6qP0W3m36YBixGQ==",
  "contentHtml": "<html>\n<head>\n\t<title></title>\n\t<link href=\"https://simbli.eboardsolutions.com/ckeditor/plugins/lance/css/annotate.css\" rel=\"stylesheet\" type=\"text/css\">\n\t<link href=\"https://simbli.eboardsolutions.com/ckeditor/plugins/lite/css/lite.css?n=1234671010\" id=\"__lite__css__\" rel=\"stylesheet\" type=\"text/css\">\n\t<link href=\"https://simbli.eboardsolutions.com/ckeditor/plugins/lite/css/opentip.css\" id=\"__lite_tt_css__\" rel=\"stylesheet\" type=\"text/css\">\n\t<link href=\"https://svc.webspellchecker.net/spellcheck31/wscbundle/css/wsc.css\" rel=\"stylesheet\" type=\"text/css\">\n</head>\n\n<body data-gramm_editor=\"false\" data-wsc-instance=\"true\">\n<p>The Board of Education recognizes the right of public school employees to form bargaining units, select an employee organization as the exclusive representative of their unit, and be represented by that organization in their employment relationship with the district. The Board is committed to negotiating in good faith with the employee organizations and respecting the rights of employees and employee organizations.</p>\n\n<p>The Superintendent or designee shall negotiate only with the exclusive representative of each bargaining unit. (Government Code <span>3543.3</span>)</p>\n\n<p>Certificated and classified employees shall not be included in the same bargaining unit. (Government Code <span>3545</span>)</p>\n\n<p>The district shall not dominate or interfere with the formation or administration of any employee organization or contribute financial or other support to it. (Government Code <span>3543.5</span>)</p>\n\n<p>Neither the district nor the employee organization shall impose or threaten to impose reprisals on employees, discriminate or threaten to discriminate against employees, or otherwise interfere with, restrain, or coerce employees because of their membership or nonmembership in an employee organization. (Government Code <span>3543.5</span>, <span>3543.6</span>)</p>\n\n<p><strong>Management and Supervisory Employees</strong></p>\n\n<p>Employees serving in a management, senior management, or confidential position shall not be represented by an exclusive representative. Such employees may represent themselves individually or may be represented by an employee organization whose membership is composed entirely of employees designated as holding those positions, but that organization shall not meet and negotiate with the district. (Government Code <span>3543.4</span>)</p>\n\n<p>However, the district may recognize a bargaining unit of supervisors if that unit includes all supervisory employees and if the unit does not represent the employee whom the supervisors supervise. (Government Code <span>3545</span>)</p>\n\n<p>Management, supervisory, and confidential positions shall be classified as follows: (Government Code <span>3540.1</span>)</p>\n\n<ol>\n\t<li>Management employee means any employee who has significant responsibilities for formulating district policies or administering district programs, and whose position is designated as a management position by the Board.<br>\n\t&nbsp;</li>\n\t<li>Supervisory employee means any employee, regardless of job description, having the authority, in the interest of the district, to hire, transfer, suspend, layoff, recall, promote, discharge, assign, reward, discipline, assign work, direct, adjust grievance of other employees, or effectively recommend that action. The exercise of this authority shall not be merely routine or clerical in nature, but shall require the use of independent judgment.<br>\n\t&nbsp;</li>\n\t<li>Confidential employee means any employee who is required to develop or present management positions with respect to employer-employee relations or whose duties normally require access to confidential information that is used to contribute significantly to the development of management positions.</li>\n</ol>\n</body>\n</html>\n",
  "contentText": "The Board of Education recognizes the right of public school employees to form bargaining units, select an employee organization as the exclusive representative of their unit, and be represented by that organization in their employment relationship with the district. The Board is committed to negotiating in good faith with the employee organizations and respecting the rights of employees and employee organizations.\n\nThe Superintendent or designee shall negotiate only with the exclusive representative of each bargaining unit. (Government Code 3543.3)\n\nCertificated and classified employees shall not be included in the same bargaining unit. (Government Code 3545)\n\nThe district shall not dominate or interfere with the formation or administration of any employee organization or contribute financial or other support to it. (Government Code 3543.5)\n\nNeither the district nor the employee organization shall impose or threaten to impose reprisals on employees, discriminate or threaten to discriminate against employees, or otherwise interfere with, restrain, or coerce employees because of their membership or nonmembership in an employee organization. (Government Code 3543.5, 3543.6)\n\nManagement and Supervisory Employees\n\nEmployees serving in a management, senior management, or confidential position shall not be represented by an exclusive representative. Such employees may represent themselves individually or may be represented by an employee organization whose membership is composed entirely of employees designated as holding those positions, but that organization shall not meet and negotiate with the district. (Government Code 3543.4)\n\nHowever, the district may recognize a bargaining unit of supervisors if that unit includes all supervisory employees and if the unit does not represent the employee whom the supervisors supervise. (Government Code 3545)\n\nManagement, supervisory, and confidential positions shall be classified as follows: (Government Code 3540.1)\n\n- Management employee means any employee who has significant responsibilities for formulating district policies or administering district programs, and whose position is designated as a management position by the Board.\n\n- Supervisory employee means any employee, regardless of job description, having the authority, in the interest of the district, to hire, transfer, suspend, layoff, recall, promote, discharge, assign, reward, discipline, assign work, direct, adjust grievance of other employees, or effectively recommend that action. The exercise of this authority shall not be merely routine or clerical in nature, but shall require the use of independent judgment.\n\n- Confidential employee means any employee who is required to develop or present management positions with respect to employer-employee relations or whose duties normally require access to confidential information that is used to contribute significantly to the development of management positions.",
  "footnotes": [
    {
      "type": "State",
      "references": [
        {
          "code": "8 CCR 33015-33490",
          "description": "Recognition of exclusive representative; proceedings",
          "url": ""
        },
        {
          "code": "8 CCR 33700-33710",
          "description": "Severance of established unit",
          "url": "https://govt.westlaw.com/calregs/Browse/Home/California/CaliforniaCodeofRegulations?guid=IB5AC9B005A0F11EC8227000D3A7C4BC3&transitionType=Default&contextData=%28sc.Default%29#IB5B0E0C35A0F11EC8227000D3A7C4BC3"
        },
        {
          "code": "Ed. Code 45060-45061.5",
          "description": "Deduction of fees from salary or wage payment; certificated employees",
          "url": "https://leginfo.legislature.ca.gov/faces/codes_displayText.xhtml?lawCode=EDC&division=3.&title=2.&part=25.&chapter=4.&article=5."
        },
        {
          "code": "Ed. Code 45100.5",
          "description": "Senior classified management positions",
          "url": "https://leginfo.legislature.ca.gov/faces/codes_displaySection.xhtml?lawCode=EDC&sectionNum=45100.5."
        },
        {
          "code": "Ed. Code 45104.5",
          "description": "Abolishment of senior classified management positions",
          "url": "https://leginfo.legislature.ca.gov/faces/codes_displaySection.xhtml?lawCode=EDC&sectionNum=45104.5."
        },
        {
          "code": "Ed. Code 45108.5",
          "description": "Definition of senior classified management employees",
          "url": "https://leginfo.legislature.ca.gov/faces/codes_displaySection.xhtml?lawCode=EDC&sectionNum=45108.5."
        },
        {
          "code": "Ed. Code 45108.7",
          "description": "Waiver of provisions of Education Code 45108.5",
          "url": "https://leginfo.legislature.ca.gov/faces/codes_displaySection.xhtml?lawCode=EDC&sectionNum=45108.7."
        },
        {
          "code": "Ed. Code 45168",
          "description": "Deduction of fees from salary or wage payment; classified employees",
          "url": "https://leginfo.legislature.ca.gov/faces/codes_displaySection.xhtml?lawCode=EDC&sectionNum=45168."
        },
        {
          "code": "Ed. Code 45220-45320",
          "description": "Merit system; classified employees",
          "url": "https://leginfo.legislature.ca.gov/faces/codes_displayexpandedbranch.xhtml?tocCode=EDC&division=3.&title=2.&part=25.&chapter=5.&article="
        },
        {
          "code": "Gov. Code 3500-3511",
          "description": "Local public employee organizations",
          "url": "https://leginfo.legislature.ca.gov/faces/codes_displayText.xhtml?lawCode=ELEC&division=9.&title=&part=&chapter=5.&article="
        },
        {
          "code": "Gov. Code 3507.7",
          "description": "Representation of temporary employees",
          "url": "https://leginfo.legislature.ca.gov/faces/codes_displaySection.xhtml?lawCode=GOV&sectionNum=3507.7."
        },
        {
          "code": "Gov. Code 3540-3549.3",
          "description": "Educational Employment Relations Act",
          "url": "https://leginfo.legislature.ca.gov/faces/codes_displayexpandedbranch.xhtml?tocCode=GOV&division=4.&title=1.&part=&chapter=10.7.&article="
        },
        {
          "code": "Gov. Code 3540.1",
          "description": "Public employment; definitions",
          "url": "https://leginfo.legislature.ca.gov/faces/codes_displaySection.xhtml?lawCode=GOV&sectionNum=3540.1."
        },
        {
          "code": "Gov. Code 3543.4",
          "description": "Management and confidential positions; representation",
          "url": "https://leginfo.legislature.ca.gov/faces/codes_displaySection.xhtml?lawCode=GOV&sectionNum=3543.4."
        },
        {
          "code": "Gov. Code 3545",
          "description": "Appropriateness of unit; basis",
          "url": "https://leginfo.legislature.ca.gov/faces/codes_displayText.xhtml?lawCode=GOV&division=4.&title=1.&part=&chapter=10.7.&article=6."
        },
        {
          "code": "Gov. Code 3550-3552",
          "description": "Prohibition on public employers deterring or discouraging union membership",
          "url": "https://leginfo.legislature.ca.gov/faces/codes_displayText.xhtml?lawCode=GOV&division=4.&title=1.&part=&chapter=11.&article="
        },
        {
          "code": "Gov. Code 3555-3559",
          "description": "Public employee communication, information and orientation",
          "url": "https://leginfo.legislature.ca.gov/faces/codes_displayText.xhtml?lawCode=GOV&division=4.&title=1.&part=&chapter=11.5.&article="
        },
        {
          "code": "Gov. Code 53260-53264",
          "description": "Employment contracts",
          "url": "https://leginfo.legislature.ca.gov/faces/codes_displayText.xhtml?lawCode=GOV&division=2.&title=5.&part=1.&chapter=2.&article=3.5."
        },
        {
          "code": "Gov. Code 6205-6210",
          "description": "Confidentiality of addresses for victims of domestic violence, sexual assault, stalking, human trafficking, child abduction, and elder or dependent adult abuse",
          "url": "https://leginfo.legislature.ca.gov/faces/codes_displayText.xhtml?lawCode=GOV&division=7.&title=1.&part=&chapter=3.1.&article="
        },
        {
          "code": "Gov. Code 6215-6216",
          "description": "Address confidentiality for individuals who face threats or violence because of work for a public entity",
          "url": "https://leginfo.legislature.ca.gov/faces/codes_displayText.xhtml?lawCode=GOV&division=7.&title=1.&part=&chapter=3.2.&article="
        },
        {
          "code": "Gov. Code 6503.5",
          "description": "Joint powers agencies; agreement",
          "url": "https://leginfo.legislature.ca.gov/faces/codes_displaySection.xhtml?lawCode=GOV&sectionNum=6503.5."
        },
        {
          "code": "Gov. Code 7928.300",
          "description": "Disclosure of employee contact information to employee organization",
          "url": "https://leginfo.legislature.ca.gov/faces/codes_displaySection.xhtml?lawCode=GOV&sectionNum=7928.300."
        }
      ]
    },
    {
      "type": "Management Resources",
      "references": [
        {
          "code": "Court Decision",
          "description": "County of Los Angeles v. Los Angeles County Employee Relations Commission (2013) 56 Cal. 4th  905",
          "url": "https://www.lexisnexis.com/clients/CACourts/"
        },
        {
          "code": "Court Decision",
          "description": "Friedrichs v. California Teachers Association, et al. (2016) 136 S.Ct. 1083",
          "url": "https://www.supremecourt.gov/opinions/opinions.aspx"
        },
        {
          "code": "Court Decision",
          "description": "Janus v. American Federation of State, County and Municipal Employees, Council 31 (2018) 138 S.Ct. 2448",
          "url": "https://www.supremecourt.gov/opinions/opinions.aspx"
        },
        {
          "code": "Public Employment Relations Board Ruling",
          "description": "Regents of the University of California (2004) PERB Dec. No. 1700-H.",
          "url": "https://perb.ca.gov/decision/1700h/#:~:text=Description%3A%20Charge%20alleged%20university%20ban,were%20violated%20by%20several%20policies."
        },
        {
          "code": "Public Employment Relations Board Ruling",
          "description": "Desert Community College District (2007) PERB Dec. No. 1921",
          "url": "https://perb.ca.gov/wp-content/uploads/decisionbank/1921E.pdf"
        },
        {
          "code": "Public Employment Relations Board Ruling",
          "description": "East Whittier School District (2004) PERB Dec. No. 1727",
          "url": "https://perb.ca.gov/decision/1727e/"
        },
        {
          "code": "Public Employment Relations Board Ruling",
          "description": "City of Sacramento (2019) PERB Dec. No. 2702",
          "url": "https://d2wu03uw2y008c.cloudfront.net/wp-content/uploads/20230821122625/decision-2702M.pdf"
        },
        {
          "code": "Website",
          "description": "CSBA District and County Office of Education Legal Services",
          "url": "https://legalservices.csba.org/"
        },
        {
          "code": "Website",
          "description": "California Federation of Teachers",
          "url": "http://www.cft.org"
        },
        {
          "code": "Website",
          "description": "California Public Employment Relations Board",
          "url": "http://www.perb.ca.gov"
        },
        {
          "code": "Website",
          "description": "California School Employees Association",
          "url": "http://www.csea.com"
        },
        {
          "code": "Website",
          "description": "California Teachers Association",
          "url": "http://www.cta.org"
        },
        {
          "code": "Website",
          "description": "Association of California School Administrators",
          "url": "http://www.acsa.org"
        },
        {
          "code": "Website",
          "description": "CSBA",
          "url": "http://www.csba.org"
        }
      ]
    }
  ],
  "crossRefs": [
    {
      "code": "0450",
      "title": "Comprehensive Safety Plan",
      "type": "AR"
    },
    {
      "code": "0450",
      "title": "Comprehensive Safety Plan",
      "type": "AR"
    },
    {
      "code": "0460",
      "title": "Local Control And Accountability Plan",
      "type": "AR"
    },
    {
      "code": "0460",
      "title": "Local Control And Accountability Plan",
      "type": "AR"
    },
    {
      "code": "1340",
      "title": "Access To District Records",
      "type": "AR"
    },
    {
      "code": "1340",
      "title": "Access To District Records",
      "type": "AR"
    },
    {
      "code": "1431",
      "title": "Waivers",
      "type": "AR"
    },
    {
      "code": "4100",
      "title": "Certificated Personnel",
      "type": "AR"
    },
    {
      "code": "4113",
      "title": "Assignment",
      "type": "AR"
    },
    {
      "code": "4113",
      "title": "Assignment",
      "type": "AR"
    },
    {
      "code": "4115",
      "title": "Evaluation/Supervision",
      "type": "AR"
    },
    {
      "code": "4115",
      "title": "Evaluation/Supervision",
      "type": "AR"
    },
    {
      "code": "4119.1",
      "title": "Civil And Legal Rights",
      "type": "AR"
    },
    {
      "code": "4119.25",
      "title": "Political Activities Of Employees",
      "type": "AR"
    },
    {
      "code": "4119.25",
      "title": "Political Activities Of Employees",
      "type": "AR"
    },
    {
      "code": "4121",
      "title": "Temporary/Substitute Personnel",
      "type": "AR"
    },
    {
      "code": "4151",
      "title": "Employee Compensation",
      "type": "AR"
    },
    {
      "code": "4154",
      "title": "Health And Welfare Benefits",
      "type": "AR"
    },
    {
      "code": "4158",
      "title": "Employee Security",
      "type": "AR"
    },
    {
      "code": "4158",
      "title": "Employee Security",
      "type": "AR"
    },
    {
      "code": "4200",
      "title": "Classified Personnel",
      "type": "AR"
    },
    {
      "code": "4200",
      "title": "Classified Personnel",
      "type": "AR"
    },
    {
      "code": "4219.1",
      "title": "Civil And Legal Rights",
      "type": "AR"
    },
    {
      "code": "4219.25",
      "title": "Political Activities Of Employees",
      "type": "AR"
    },
    {
      "code": "4251",
      "title": "Employee Compensation",
      "type": "AR"
    },
    {
      "code": "4254",
      "title": "Health And Welfare Benefits",
      "type": "AR"
    },
    {
      "code": "4258",
      "title": "Employee Security",
      "type": "AR"
    },
    {
      "code": "4258",
      "title": "Employee Security",
      "type": "AR"
    },
    {
      "code": "4300",
      "title": "Administrative And Supervisory Personnel",
      "type": "AR"
    },
    {
      "code": "4301",
      "title": "Administrative Staff Organization",
      "type": "AR"
    },
    {
      "code": "4312.1",
      "title": "Contracts",
      "type": "AR"
    },
    {
      "code": "4315",
      "title": "Evaluation/Supervision",
      "type": "AR"
    },
    {
      "code": "4319.1",
      "title": "Civil And Legal Rights",
      "type": "AR"
    },
    {
      "code": "4351",
      "title": "Employee Compensation",
      "type": "AR"
    },
    {
      "code": "4354",
      "title": "Health And Welfare Benefits",
      "type": "AR"
    },
    {
      "code": "4358",
      "title": "Employee Security",
      "type": "AR"
    },
    {
      "code": "4358",
      "title": "Employee Security",
      "type": "AR"
    },
    {
      "code": "9000",
      "title": "Role Of The Board",
      "type": "AR"
    }
  ],
  "attachments": []
}
