{
  "school": "Henry Ford Elementary School",
  "schoolYear": "2025-26",
  "consolidatedAppFunds": 0,
  "csiFunds": 0,
  "totalBudgeted": 680588,
  "federalPrograms": [
    {
      "name": "Title I",
      "amount": 61211
    }
  ],
  "stateLocalPrograms": [
    {
      "name": "D100",
      "amount": 21627
    },
    {
      "name": "District Funded",
      "amount": 249047
    },
    {
      "name": "Measure U",
      "amount": 146727
    },
    {
      "name": "None Specified",
      "amount": 0
    },
    {
      "name": "Parent-Teacher Association (PTA)",
      "amount": 74500
    },
    {
      "name": "Prop. 28",
      "amount": 74560
    },
    {
      "name": "Site Formula Funds",
      "amount": 52916
    }
  ]
}
